LICENSE.txt
MANIFEST.in
README.md
README.txt
setup.py
pygsw/__init__.py
pygsw/ctd.pyx
pygsw/practical_salinity.pyx
pygsw/pygsw.h
pygsw/seawater.pyx
pygsw/vectors.py
pygsw/version.py
pygsw.egg-info/PKG-INFO
pygsw.egg-info/SOURCES.txt
pygsw.egg-info/dependency_links.txt
pygsw.egg-info/top_level.txt
pygsw/src/ctd.c
pygsw/src/sp_from_c.c
pygsw/test/__init__.py
pygsw/test/test_pygsw.py