Metadata-Version: 1.1
Name: pygsw
Version: 0.0.10
Summary: Python bindings for the TEOS-10 V3.0 GSW Oceanographic Toolbox in C
Home-page: https://github.com/lukecampbell/pygsw/
Author: Luke Campbell
Author-email: luke.s.campbell@gmail.com
License: LICENSE.txt
Keywords: oceanography,seawater
Platform: UNKNOWN
Classifier:  Intended Audience :: Science/Research
Classifier: Intended Audience :: Developers
Classifier: Intended Audience :: Education
Classifier: Operating System :: OS Independent
Classifier: Programming Language :: Python
Classifier: Topic :: Scientific/Engineering
Classifier: Topic :: Education
Classifier: Topic :: Software Development :: Libraries :: Python Modules
